jquants_ml/__init__.py
jquants_ml/ml.py
jquants_ml-0.1.4.dist-info/LICENCE.txt
jquants_ml-0.1.4.dist-info/METADATA
jquants_ml-0.1.4.dist-info/WHEEL
jquants_ml-0.1.4.dist-info/top_level.txt
jquants_ml-0.1.4.dist-info/RECORD
